{"stats":{"minecraft:used":{"minecraft:salmon":1,"minecraft:dark_oak_planks":1,"minecraft:chicken":1},"minecraft:mined":{"minecraft:grass":3,"minecraft:dark_oak_leaves":4,"minecraft:dark_oak_log":7},"minecraft:picked_up":{"minecraft:feather":1,"minecraft:chicken":1,"minecraft:salmon":1,"minecraft:dark_oak_log":5},"minecraft:crafted":{"minecraft:dark_oak_planks":20},"minecraft:custom":{"minecraft:time_since_rest":14574,"minecraft:sprint_one_cm":60902,"minecraft:crouch_one_cm":1820,"minecraft:play_time":14574,"minecraft:walk_one_cm":19900,"minecraft:sneak_time":462,"minecraft:walk_under_water_one_cm":607,"minecraft:mob_kills":2,"minecraft:jump":183,"minecraft:damage_dealt":105,"minecraft:leave_game":2,"minecraft:time_since_death":14574,"minecraft:walk_on_water_one_cm":1424,"minecraft:total_world_time":14574,"minecraft:swim_one_cm":5027,"minecraft:fall_one_cm":5368,"minecraft:fly_one_cm":31805},"minecraft:killed":{"minecraft:chicken":1,"minecraft:salmon":1}},"DataVersion":3465}